Workbook

Sheet Read me
A1: AI-detection screen of the 2026 Arizona Voter Education Guide
A2: Prepared by Luke Basler
A4: What this is
A5: I screened every candidate statement in the Arizona Citizens Clean Elections Commission's 2026 General
A6: Election Voter Education Guide for AI-generated text with Pangram 4.0.
A7: 208 candidates appear in the guide and 198 submitted a statement.
A9: What the AI score means
A10: Pangram returns 'fraction_ai': the share of the statement it attributes to a language model,
A11: from 0.00 (no text classified as AI-generated; AI-assisted text may still be present) to 1.00 (entirely AI) - that is column I in the "Candidates" tab. Column J is Pangram's own three-way label.
A12: A statement is counted as FLAGGED here when the AI score is above 0.50. That threshold is
A13: mine, not Pangram's.
A15: Reported accuracy
... A22: Because there are so few Green, Independent and No Labels statements, comparisons involving them are likely not statistically significant.

Sheet Candidates
A1: Candidate | B1: Party | C1: Office | D1: District | E1: Race type | F1: Chamber | G1: PDF page (printed page + 2) | H1: Words | I1: Pangram AI score | J1: Pangram label | K1: Flagged (>0.50) | L1: Statement
A2: Kris Mayes | B2: Democratic | C2: Attorney General | E2: Statewide | G2: 26 | H2: 194 | I2: 0 | J2: Human | K2: =IF(I2="","no statement",IF(I2>0.5,"Yes","No")) -> No | L2: I have fought like hell for Arizonans protecting seniors from scams and abuse, stopping the flow of deadly fentanyl, lowering prices, blocking mega-mergers, and addressing rising rent. By working with local police, sheriffs, and federal partners, I have seized 27 million pills of fentanyl and protected Arizonans from drug smugglers and scammers. To defend our groundwater, I sued a Saudi-owned mega farm for excessive groundwater pumping harming rural neighbors and ranchers. I blocked the Albertson and Kroger merger preventing job loss, higher grocery prices, and exacerbated food deserts.I have intervened against APS and TEP’s unfair 14% rate hike and cracked down on billions in Medicaid fraud, successfully reducing fraudulent billing by 92%. My federal lawsuits have saved Arizonans $1.5 billion in taxpayer dollars by protecting Headstart, Meals on Wheels, and Americorps. My record at the U.S Supreme Court on behalf of Arizona is 2-0, overturning illegal tariffs costing Arizonans an average $1,500 a year. As a daughter of rural Arizona, I have held over 50 town halls across all 15 counties. It’s critical to reelect me as your Attorney General, so I can keep protecting Arizona families and making life more affordable in Arizona.
A3: Warren Petersen | B3: Republican | C3: Attorney General | E3: Statewide | G3: 26 | H3: 197 | I3: 0 | J3: Human | K3: =IF(I3="","no statement",IF(I3>0.5,"Yes","No")) -> No | L3: I will restore the Attorney General’s Office to its mission: fighting crime, combatting fraud and corruption, and defending our Constitution. I am the only candidate endorsed by Arizona’s largest law enforcement organizations, making my opponent the first incumbent Attorney General to be rejected by law enforcement because of her explosive temper, soft-on-crime positions, and dangerous rhetoric towards officers. With more than a decade of legal experience, including prosecution, lawmaking, and serving as Judiciary and Rules Chairman, and Senate President, I have stepped in to manage more than 130 cases and amicus briefs when Mayes refused to defend Arizona laws. As the de facto AG, I successfully took Arizona’s Save Women’s Sports Act to the U.S. Supreme Court to keep men out of women’s sports. I have protected Arizonans from sex offenders and open borders when Mayes failed to act. Under Mayes, the office has become partisan and political, and while she blames others for rising prices, her extreme environmental votes as an Arizona Corporation Commissioner have driven up costs. Already leading a major branch of government, I have the legal experience, leadership, and judgment to be Attorney General on day one. I respectfully ask for your vote.
A4: Clara Pratte | B4: Democratic | C4: Corporation Commissioner | E4: Statewide | G4: 31 | H4: 179 | I4: 1 | J4: AI | K4: =IF(I4="","no statement",IF(I4>0.5,"Yes","No")) -> Yes | L4: I’m running for the Arizona Corporation Commission because I’ve lived the consequences of decisions made in this office. Growing up on the Navajo Nation without electricity or running water, I understand how essential reliable and affordable utilities are to everyday life. Today, too many Arizona families, ranging from rural communities to our cities, are struggling with rising costs and uncertainty about the future. I’ve spent my career working in energy, economic development, and now as a small business owner, helping bring infrastructure and opportunity to communities that have been overlooked. Communities just like my hometown. It's why I believe the Commission should be a watchdog for the people by ensuring fair rates, reliable service, and encouraging smart investments that strengthen our economy while protecting our air and water. We can expand clean, cost-effective energy, create good-paying jobs, and protect our natural resources while keeping Arizona competitive. We just need the political courage to do so. I’m running to fight for affordable utility bills, limit data centers, and protect our water. I hope to have the honor of your vote.
A5: Jonathon Hill | B5: Democratic | C5: Corporation Commissioner | E5: Statewide | G5: 30 | H5: 146 | I5: 1 | J5: AI | K5: =IF(I5="","no statement",IF(I5>0.5,"Yes","No")) -> Yes | L5: I’m running for the Arizona Corporation Commission because too many Arizonans are paying more every month and seemingly getting less in return. As a scientist who has spent my career working on complex systems and solving real-world problems, I believe we need leadership that is grounded in facts, transparency, and accountability. The Commission has enormous influence over our utility bills, our energy reliability, and our long-term economic competitiveness, yet too often it has failed to ask tough questions or fully represent ratepayers. I’m not running as a career politician; I’m running as someone who believes government should work for people, not special interests. We can lower costs, strengthen our grid, and invest in cleaner, more efficient energy that protects our water and air while supporting business growth. Arizona deserves leadership that is practical, forward-thinking, and focused on results. That’s what I will bring to the Commission.
A6: Kevin Thompson | B6: Republican | C6: Corporation Commissioner | E6: Statewide | G6: 31 | H6: 199 | I6: 0 | J6: Human | K6: =IF(I6="","no statement",IF(I6>0.5,"Yes","No")) -> No | L6: One office that shouldn’t be political is the regulators who oversee utilities and our grid. My focus is protecting ratepayers and grid stability. I’ve championed an all-of-the above energy approach to manage Arizona’s energy grid, focusing on eliminating Green New Deal policies that have cost customers billions of dollars in extra surcharges, while pushing for greater ratepayer protections and holding utilities accountable for wasteful and frivolous spending. I championed the elimination of previously enacted Commission mandates that forced utilities to fund energy projects and programs costing ratepayers nearly $4Billion since their inception. I led the charge in eliminating over $50Million in ratepayer surcharges from the state’s largest electric utility in incentives for things like electric golf carts, EV charging stations, and payments to homebuilders to install appliances. I’ve worked tirelessly to remove regulatory barriers and mandates to unleash energy innovation, while ensuring grid stability and maintaining reliable energy supply. Under my watch, Arizona’s grid is now ranked the 7th most reliable in the country. I recently led the charge to prevent ratepayers from being saddled with $1.9Billion in extra costs to open a shuttered power plant and have worked on federal permitting reform for natural gas and nuclear power.
A7: Mike Cease | B7: Green | C7: Corporation Commissioner | E7: Statewide | G7: 30 | J7: no statement | K7: =IF(I7="","no statement",IF(I7>0.5,"Yes","No")) -> no statement | L7: (none submitted)
A8: Ralph Heap | B8: Republican | C8: Corporation Commissioner | E8: Statewide | G8: 30 | H8: 162 | I8: 1 | J8: AI | K8: =IF(I8="","no statement",IF(I8>0.5,"Yes","No")) -> Yes | L8: Ralph Heap was elected to the Arizona House of Representatives, where he has been a strong voice for limited government, free markets, medical freedom, and parental rights. Now, as a candidate for the Arizona Corporation Commission, Dr. Heap is ready to stand up for ratepayers, defend rural communities, and block the encroachment of globalist energy agendas. As Corporation Commissioner, Dr. Heap will: • Fight against ESG mandates and California-style energy experiments • Oppose unnecessary utility rate increases that punish families and seniors • Ensure a reliable, diverse energy grid — not one dictated by ideology • Fully Support the Trump Energy Agenda, with emphasis on fossil fuels and Nuclear energy. • • Protect water access and infrastructure, especially in rural Arizona • Demand transparency and stand against special interest influence at the Commission With decades of real-world experience, a commitment to constitutional principles, and a heart for service, Dr. Ralph Heap is the steady, conservative leader Arizona needs at the Corporation Commission.
A9: Andy Biggs | B9: Republican | C9: Governor | E9: Statewide | G9: 20 | H9: 95 | I9: 0 | J9: Human | K9: =IF(I9="","no statement",IF(I9>0.5,"Yes","No")) -> No | L9: Andy Biggs is running for Governor to bring down costs for Arizona families and businesses by growing our economy, lowering taxes, encouraging job growth, and reducing government interference. As Governor, he will prioritize the use and expansion of reliable and affordable energy sources for every Arizonan and responsibly manage our water and land resources to ensure long-term growth and an increased supply of single-family homes. Biggs will protect the rights and freedoms of Arizonans to make their own education and health choices, supporting school choice policies and enacting the MAHA agenda at the state level.
A10: Katie Hobbs | B10: Democratic | C10: Governor | E10: Statewide | G10: 20 | H10: 194 | I10: 0 | J10: Human | K10: =IF(I10="","no statement",IF(I10>0.5,"Yes","No")) -> No | L10: As governor, Katie Hobbs has put politics aside and focused on tackling the tough challenges facing Arizona. As Washington, D.C. policies raise costs on everything from healthcare to groceries to gas, Katie is fighting to make life more affordable for Arizona families. She passed middle-class tax cuts that save 88% of Arizonans money, give seniors an additional $6,000 deduction, and eliminate taxes on tips and overtime pay. She repealed the tax on rent, helped first-time homebuyers afford down payments, and cut red tape to make housing more affordable. While Washington politicians have slashed healthcare, Katie eliminated medical debt for nearly 700,000 Arizonans and lowered prescription drug costs by up to 80%. She stood up to her own party and the federal government to secure Arizona’s water and canceled leases allowing a Saudi-owned corporation to pump Arizona’s groundwater unchecked. She’s worked with law enforcement to seize over 18 million fentanyl pills, fight human trafficking, and combat cartels throughout Arizona. Katie knows there’s more work to do, and she’ll keep standing up to Washington and her own party to put Arizona first and fight to lower costs, keep communities safe, and create opportunity for every Arizonan.
A11: Risa Lombardo | B11: Green | C11: Governor | E11: Statewide | G11: 21 | H11: 197 | I11: 0 | J11: Human | K11: =IF(I11="","no statement",IF(I11>0.5,"Yes","No")) -> No | L11: Risa Lombardo is running for Governor because she knows families are struggling, and Katie Hobbs and the Republicans are too busy squabbling to fix things. As Governor, Lombardo will transform our broken two -party system into a state government that serves the people, not greed or corporate interests. She will protect our fragile democracy from those who overstep their legal authority and from those who attack it to further their political ambitions. She will stop the Data Centers that Republican and Democrats are allowing to happen without proper consideration of the costs, water and energy demands involved. She will end the use of Flock Cameras to track Arizona residents’ every movement across the state as we merely drive through our communities. She will stop discrimination by race, class, gender, sexual orientation, age, nationality, or religion. She will combat Climate Change, protect our environment, and ensure policies that create clean air and clean water for Arizona residents. And she will reduce the costs of utilities for working families. Hobbs and the Republicans are too busy fighting to find common ground. Shatter this two-party system and change Arizona politics forever! Risa Lombardo would be honored to have your vote.
A12: Teri Ann Hourihan | B12: No Labels | C12: Governor | E12: Statewide | G12: 21 | H12: 193 | I12: 1 | J12: AI | K12: =IF(I12="","no statement",IF(I12>0.5,"Yes","No")) -> Yes | L12: Teri Ann chose to run as an Independent/No Labels candidate because she believes political division has prevented meaningful solutions and left too many Arizonans behind. She is committed to putting people before politics and leading with honesty, integrity, accountability, and common sense—not party agendas, special interests, or wealthy donors. Teri Ann has pledged never to accept PAC or AIPAC donations because she believes elected officials should be accountable to the people they serve. As Governor, she will restore public trust by reforming state government, increasing transparency, and ensuring agencies operate efficiently and responsibly. Her priorities include lowering the cost of living, protecting the rights of all people, expanding affordable childcare, protecting school choice while increasing accountability for education spending, securing Arizona's water future, reducing homelessness through shelter and support services, strengthening the family court system, supporting rural communities, improving legal immigration processes, and eliminating fraud, waste, and abuse in government. Above all, Teri Ann believes leadership begins with listening. She is committed to being accessible, accountable, and responsive to every Arizonan while delivering practical, bipartisan solutions that unite communities, restore trust in government, and improve the quality of life for families across Arizona.
A13: Angela Harrolle Mohan (Hourihan) | B13: Independent | C13: Lieutenant Governor | E13: Statewide | G13: 23 | H13: 163 | I13: 0.21130435 | J13: Mixed | K13: =IF(I13="","no statement",IF(I13>0.5,"Yes","No")) -> No | L13: Political: Angela is not a career politician but a citizen inspired to serve after witnessing the challenges facing everyday Arizonans. She believes government works best when leaders focus on practical solutions rather than partisan politics. She successfully championed bipartisan legislation signed into law.. A registered Independent, Angela has previously been registered as both a Democrat and Republican to participate in their primary elections, reflecting her belief that leadership should be driven by people, solutions, and results—not party labels. She believes protecting public safety is a commitment owed to every Arizonan. Personal: Angela is happily remarried and enjoys spending time with her family, including her six children and newest grandchild. Through years of international travel and government missions, she worked with diverse communities, including Spanish-speaking populations, strengthening her ability to connect across cultures. In 2008, her late husband was killed during a mountain rescue in Sedona while saving the lives of two others. His sacrifice continues to inspire her lifelong commitment to public service.
A14: John Giles (Hobbs) | B14: Independent | C14: Lieutenant Governor | E14: Statewide | G14: 22 | H14: 199 | I14: 0 | J14: Human | K14: =IF(I14="","no statement",IF(I14>0.5,"Yes","No")) -> No | L14: John Giles, a former Republican and now Independent, is running alongside Katie Hobbs to continue delivering real results by setting partisan politics aside and putting Arizona first. They believe our challenges are not Democrat or Republican issues – they’re Arizona issues that deserve Arizona solutions. Together, they will fight to bring down costs that keep rising because of Washington’s reckless policies. As governor, Katie has cut taxes each year for middle-class families, small businesses, and veterans. She repealed the tax on rent and cut red tape to make housing more affordable. While Washington politicians have raised healthcare costs and slashed coverage, Katie eliminated medical debt for nearly 700,000 Arizonans and lowered prescription drug costs by up to 80%. She stood up to her own party and the federal government to secure Arizona’s water and canceled leases allowing a Saudi-owned corporation to pump Arizona’s groundwater unchecked. She’s worked with law enforcement to seize over 18 million fentanyl pills, fight human trafficking, and combat cartels throughout Arizona. John and Katie share the same approach to leadership: put Arizona first, find common ground, and deliver results. Together, they’ll lower costs, protect our freedoms, keep communities safe, and create opportunity for every Arizonan.
A15: Lisa Castillo (Lombardo) | B15: Green | C15: Lieutenant Governor | E15: Statewide | G15: 22 | H15: 200 | I15: 1 | J15: AI | K15: =IF(I15="","no statement",IF(I15>0.5,"Yes","No")) -> Yes | L15: I am running for Lieutenant Governor alongside Risa Lombardo because Arizona families deserve leadership grounded in compassion, honesty, and common sense. Too many people struggle to afford housing, healthcare, education, food, and other necessities while feeling that government no longer listens to them. I will advocate for practical, humane solutions to homelessness that provide immediate assistance while addressing the causes of housing instability. I will support stronger mental-health services, including accessible treatment, crisis intervention, community programs, and stable housing. These investments can save lives, strengthen families, and make our communities safer. As a small-business owner, wife, mother, and Arizona resident since 2010, I understand the pressures families face and the importance of responsible decisions. I support the Green Party values of environmental responsibility, social justice, grassroots democracy, peace, and respect for diversity. Public service begins with listening. I will work with Arizonans from every background, treat people with dignity, and seek solutions that improve everyday life. I will put people, community well-being, and Arizona’s long-term future ahead of political games. Together, we can build an Arizona where opportunity is shared, communities are healthy, government is accountable, and every person has a fair chance to create a secure and hopeful future.
A16: Sine Kerr (Biggs) | B16: Republican | C16: Lieutenant Governor | E16: Statewide | G16: 23 | H16: 92 | I16: 0 | J16: Human | K16: =IF(I16="","no statement",IF(I16>0.5,"Yes","No")) -> No | L16: Arizona is a great state, one where my husband Bill and I raised our family and built a business. But under Katie Hobbs, the Arizona we know has come under attack. She’s raised costs, made life more difficult; and threatened the livelihood of rural Arizonans. As the Lt. Governor for Andy Biggs, I’ll make sure every Arizonan has a voice no matter where they live and how they make a living. The Biggs/Kerr ticket will put more money in your pocket, keep our state safe, and Restore the American Dream in Arizona.
A17: Adrian Fontes | B17: Democratic | C17: Secretary Of State | E17: Statewide | G17: 24 | H17: 196 | I17: 0 | J17: Human | K17: =IF(I17="","no statement",IF(I17>0.5,"Yes","No")) -> No | L17: As Secretary of State, I’ve delivered on key promises to strengthen election integrity, ensure voter access, improve business services, and promote transparency. In everything I do, my goal is to protect your vote. These efforts include launching a statewide ballot tracking system that allows voters to receive text and email updates when their ballots are sent and received. I have fought to protect your private data and vote-by-mail because nobody should have to stand in long lines in the heat to cast their vote. Ahead of the 2024 election, I hosted statewide tabletop exercises with election officials, law enforcement, and cybersecurity experts to prepare for potential threats, including emerging challenges like deepfakes and content authentication. To combat misinformation, I established the Artificial Intelligence and Election Security Advisory Committee, bringing together leaders from academia, business, and technology to assess risks and identify opportunities. In 2025, I received a Clearie Award from the U.S. Election Assistance Commission for the third consecutive year, honoring innovation and excellence in election administration. Importantly, I successfully oversaw the peaceful administration and certification of the 2024 election, reinforcing trust in Arizona’s democratic process. I would be honored to earn your vote. Thank you.
A18: Alexander Kolodin | B18: Republican | C18: Secretary Of State | E18: Statewide | G18: 25 | H18: 199 | I18: 0 | J18: Human | K18: =IF(I18="","no statement",IF(I18>0.5,"Yes","No")) -> No | L18: As Secretary of State, my sole focus will be on serving all voters, regardless of political affiliation, and administering elections that are secure, transparent, honest, and follow the law, while delivering fast results that all Arizonans can have confidence in on election night. I’ve been fighting for Arizonans’ civil liberties, including the right to free and fair elections, for well over a decade. As an experienced election attorney, I’ve successfully challenged my opponent Adrian Fontes’ numerous and repeated violations of the law in court. As a member of the Arizona House of Representatives, I’ve been the state’s most successful election policy-focused legislator — achieving broad bipartisan support for some of the most important election laws in state history. I’ve fought to protect the voting rights of military members, veterans, the disabled, rural voters, and voters from every Party, income level, race, gender and age. The reality is that the process of administering elections shouldn’t be about right vs. left or rich vs. poor. Election administration is about following the law, running world class elections, and delivering fast results that voters can trust. I’m Alex Kolodin and I’m humbly asking for your vote to be Arizona’s next Secretary of State.
A19: Duwayne Collier | B19: Green | C19: Secretary Of State | E19: Statewide | G19: 24 | H19: 143 | I19: 0 | J19: Human | K19: =IF(I19="","no statement",IF(I19>0.5,"Yes","No")) -> No | L19: Duwayne Collier is the Green Party nominee for Secretary of State. For too long our elections have been regulated by the two party system for their own gain. As the Secretary of State for Arizona, Duwayne Collier will work to end the two party monopoly by pushing for ranked-choice voting, open debates, easier ballot access, public financing, election transparency, and voter access. Democracy should not belong to the highest bidder, or billionaires’ ruling influence. Democracy belongs to the voters. As a representative of the people, Collier will fight to ensure that every vote is counted, results are fast and accurate, and that your vote is heard! Collier will work for a system that encourages strong third parties and ends special interests and corporate influence over elections. Duwayne Collier would be honored to have your vote to reform Arizona and represent you, the people!
... A25: Teresa Leyba Ruiz | B25: Democratic | C25: Superintendent Of Public Instruction | E25: Statewide | G25: 28 | H25: 201 | I25: 0 | J25: Human | K25: =IF(I25="","no statement",IF(I25>0.5,"Yes","No")) -> No | L25: Dr. Ruiz is proud to be the only educator running for Superintendent and believes a teacher — not a career politician — should oversee Arizona’s public schools. Her priorities include increasing transparency and accountability, protecting taxpayer dollars, stabilizing the teacher workforce, upholding high academic standards with strong support systems, and expanding career and post-secondary training opportunities. As a former community college president, Terry has managed operating budgets larger than the Arizona Department of Education with transparency and fiscal responsibility. She will bring that same leadership to the office by strengthening oversight of the ESA program, ending the automatic approval of purchases, implementing automated solutions, and creating a public transparency portal so taxpayers can see how funds are spent. After listening to educators in all 15 Arizona counties, Terry plans on supporting her fellow teachers through professional development, mentorship, and advocacy for competitive pay. As Superintendent, she will expand opportunities for all students in the K-12 system from early literacy and math interventions, to increased access to career and technical education and dual enrollment pathways. Dr. Ruiz believes that when our schools succeed, our state succeeds, and will focus on real results for our students — not political agendas and empty rhetoric.
A26: Quang Huu Nguyen | B26: Republican | C26: State Representative - District 1 | D26: 1 | E26: Legislative | F26: House | G26: 33 | H26: 189 | I26: 0 | J26: Human | K26: =IF(I26="","no statement",IF(I26>0.5,"Yes","No")) -> No | L26: I ran for office as a Constitutional Conservative, you trusted and elected me, and I’ve gone to work each day and KEPT MY WORD! That means real election integrity measures, secure borders (finishing that wall), criminalizing fentanyl dealers, fighting for affordability, medical freedom, safe neighborhoods, improved highways and transportation (improving I-17), long-term water security, and personal liberty. I have a 100% pro- gun, pro-Constitution, pro-life, pro-school choice, and pro-Arizona voting record. I’ve worked closely with Representative Selina Bliss and our district is home to Arizona’s most reliably conservative State Reps. We are again being challenged from our left by the same candidate you rejected last time, but that’s okay. Voters should have choices, and we’re going to keep voting for conservative ideals no matter who runs against us. You know me, and you know the love I have for my country, my state, and everyone who calls it home. If you want a proven America First team, then I ask you to cast your TWO State House votes for Nguyen AND Bliss. On behalf of my wonderful wife and kids, THANK YOU! And may God continue to bless America.
A27: Sandy Zalecki | B27: Democratic | C27: State Representative - District 1 | D27: 1 | E27: Legislative | F27: House | G27: 34 | H27: 198 | I27: 0 | J27: Human | K27: =IF(I27="","no statement",IF(I27>0.5,"Yes","No")) -> No | L27: I have never wanted to be a politician, but I found out that being in politics is one of the best ways to help others if it's done properly. I'm not good a making big promises that I can't keep. I don't like to lie. If I were elected there are four things that I would work to change. One would be to require every state candidate to run clean elections. It would make it more fair and take some of the dirty money out of politics. Second, water. We haven't had any water legislation since the 1980 Ground Water Act. It needs to be updated to insure abundant water for our future. Third, affordability. We have an affordability crisis in Arizona that our current legislature refuses to acknowledge. Fourth, education. We are 49th in spending on education. We have 100 million dollars in fraud because of ESA vouchers. Our children deserve better from us. They are our future. According to Markers for Democracy "Arizona's state legislature is one of the most reactionary and harmful in the nation." Something needs to change and I would like to be one of the ones that helps make the needed changes.
A28: Selina Bliss | B28: Republican | C28: State Representative - District 1 | D28: 1 | E28: Legislative | F28: House | G28: 33 | H28: 200 | I28: 0 | J28: Human | K28: =IF(I28="","no statement",IF(I28>0.5,"Yes","No")) -> No | L28: As I wrap up my second term in office, I am happy to report I’ve kept my promises and built a strong conservative record on issues that matter to Arizona voters. Working with my seatmate, Representative Quang Nguyen, I prioritized efforts to boost the Arizona economy and fight inflation, secure our border and enforce our laws, and restore integrity to our election process. I have demonstrated a 100% pro-2nd Amendment record, led to secure our water future, fought to protect life, and prioritized both veterans and first responders. I also used my background as a nurse and educator to lead on healthcare issues and support medical freedom, while reducing fraud, waste, and abuse, and working to improve our schools and universities. I’ve lived in this District since 1971 and have been involved with a variety of political, civic, and charitable organizations. I’m committed to public service and am grateful for the trust you have placed in me. You have TWO votes for the State House, and I hope I can count on you to cast one vote for me so I can return to work alongside Representative Quang Nguyen to prioritize LD1 and keep Arizona great! I appreciate your support!
A29: Christine Ellen Dargon | B29: Democratic | C29: State Senator - District 1 | D29: 1 | E29: Legislative | F29: Senate | G29: 32 | H29: 201 | I29: 1 | J29: AI | K29: =IF(I29="","no statement",IF(I29>0.5,"Yes","No")) -> Yes | L29: Legislative District 1 deserves a senator who actually works for the people who live here and right now, we don't have one. Our current senator parachuted into this district after losing a statewide race and has spent his time denying elections, banning abortion with no exceptions for rape or incest, chasing national headlines while LD1's real problems go unaddressed. He does not work for you - I will! Our wells are failing as aquifers are drawn down by unregulated corporate pumping. Our schools are among the most underfunded in the nation. Families are driving two hours for basic medical care. These are not unsolvable problems. I will fight for groundwater protections that put LD1 families before corporate extraction interests. I will fight to fully fund our public schools and pay teachers what they deserve. I will fight to expand rural healthcare access so that a medical emergency doesn't also become a financial one or a tragedy because help is hours away. I will fight for zoning reforms that remove unnecessary barriers to workforce and affordable housing development, state investment in rural housing infrastructure, and tenant protections that keep working families stably housed. Solutions over stunts. Community over career. No special interests.
A30: Mark Finchem | B30: Republican | C30: State Senator - District 1 | D30: 1 | E30: Legislative | F30: Senate | G30: 32 | J30: no statement | K30: =IF(I30="","no statement",IF(I30>0.5,"Yes","No")) -> no statement | L30: (none submitted)
A31: Justin Wilmeth | B31: Republican | C31: State Representative - District 2 | D31: 2 | E31: Legislative | F31: House | G31: 37 | H31: 200 | I31: 0 | J31: Human | K31: =IF(I31="","no statement",IF(I31>0.5,"Yes","No")) -> No | L31: Howdy everyone! I have had the honor of serving in the Arizona House of Representatives for the past six years. I've spent that time fighting against overreaching COVID mandates, lowering taxes, eliminating burdensome regulations, improving housing affordability and, yes, making Pluto the State Planet. I've been chairman of the House Commerce Committee, where I focused on improving economic development and bringing more jobs to the district. Currently, I serve as the chairman of the House Artificial Intelligence & Innovation Committee, where I am helping guide the way on the new digital policy frontier. I want to help this technology be more beneficial to you! I've spent my entire career in public policy. I've worked a combined 12 years at two different state legislatures, including here in Arizona, where I was a policy staffer for the Republican Caucus. I also worked at Americans for Prosperity, a Conservative entity focused on lowering taxes, regulations and shrinking government wherever possible. I'm very proud to say I'm an effective Legislator for our district and I understand how to get the job done. I want to ensure Arizona continues to be friendly for free markets and individual liberties! I look forward to earning your support.
A32: Paul Carver | B32: Republican | C32: State Representative - District 2 | D32: 2 | E32: Legislative | F32: House | G32: 36 | H32: 195 | I32: 1 | J32: AI | K32: =IF(I32="","no statement",IF(I32>0.5,"Yes","No")) -> Yes | L32: As President of the Deer Valley Unified School District Governing Board, I have spent my tenure championing transparency, parental rights, and fiscal accountability in public education. Now, I am asking for your vote to bring that same principled, results-oriented leadership to the Arizona House of Representatives for Legislative District 2. Our community faces vital challenges that demand practical, battle-tested solutions. As a Marine Corps veteran, business analyst, and father, I understand the direct impact of state policy on our families, local businesses, and neighborhood schools. My platform centers on four core pillars: protecting taxpayer dollars through strict fiscal discipline, empowering parents to make the best educational choices for their children, strengthening public safety by fully supporting law enforcement, and addressing critical water concerns to secure the future of the Valley. After earning my place on the general election ballot through a successful primary write-in effort, I am deeply honored by the grassroots support of our community. Legislative District 2 deserves a representative who listens, operates with integrity, and delivers accountable governance. I promise to work tirelessly at the State Capitol to safeguard your freedom and build a stronger Arizona. I respectfully ask for your vote.
A33: Stephanie Simacek | B33: Democratic | C33: State Representative - District 2 | D33: 2 | E33: Legislative | F33: House | G33: 36 | H33: 180 | I33: 0 | J33: Human | K33: =IF(I33="","no statement",IF(I33>0.5,"Yes","No")) -> No | L33: I am a mom, public school teacher, Deer Valley Unified School District governing board member, and an Arizona State House Representative. I first ran for office to strengthen public education, address our water crisis, and tackle rising costs, including childcare, healthcare, and housing. Since my election in 2024, I have had the honor and privilege to fight for these issues on behalf of Arizona’s second legislative district. These are not partisan issues; they affect us all, regardless of our political affiliation. As a public school teacher, I saw firsthand the positive impact of diverse teaching methods, dedicated staff, and engaged parents. As a mother, I’ve felt how hard rising costs in healthcare, housing, childcare, food, and utilities have hit Arizona families. As an Arizonan, I know we must act fast to ensure that future generations get to enjoy this great state we all know and love. I am seeking reelection this year because our work is far from finished. There is still so much we can do, and I remain committed to continuing that work on behalf of my neighbors.
A34: Amelia Gallitano | B34: Democratic | C34: State Senator - District 2 | D34: 2 | E34: Legislative | F34: Senate | G34: 35 | H34: 190 | I34: 0 | J34: Human | K34: =IF(I34="","no statement",IF(I34>0.5,"Yes","No")) -> No | L34: My name is Amelia Gallitano. I’m a doctor, neuroscientist, professor, and mom. I moved here 19 years ago with my two sons to be a professor at the University of Arizona College of Medicine in Phoenix, and I’ve been educating new doctors ever since. I also cared for veterans with PTSD at the Phoenix VA for years. It does not take a PhD in neuroscience to see that something is very wrong in our legislature. Lawmakers are giving tax breaks to private plane owners while everyday Arizonans struggle to make ends meet. They are giving away a billion dollars with no accountability to private school vouchers while attacking the public schools that 90% of Arizona families choose. They want to take away Vote by Mail, which more than 75% of voters rely on. I’ve spent my life in public service, and I’m stepping up to work for everyday Arizonans. I will make healthcare more affordable, support our public schools and teachers, and stop corporations from driving up housing and energy costs. It’s time for a state senator focused on people, not corporate profits. I would be honored to represent you.
A35: Shawnna Bolick | B35: Republican | C35: State Senator - District 2 | D35: 2 | E35: Legislative | F35: Senate | G35: 35 | H35: 152 | I35: 0 | J35: Human | K35: =IF(I35="","no statement",IF(I35>0.5,"Yes","No")) -> No | L35: Actions and accomplishments speak louder than empty promises. Since 2019, I have represented you with a common-sense voice at the State Capitol. I have supported legislation to secure our border, reduce taxes, and improve affordability. I led the fight to make housing more affordable, lower inflation on our food and housing, and voted to pass one of the largest tax cuts in state history. I am proud of my votes to invest in our schools and teachers, fight drug trafficking and fentanyl, advance consumer protection, and end child sex trafficking. As a mom, tackling public safety issues is personal to me - and critical for our community. I will continue to champion commonsense solutions to the challenges facing our community, from standing up for veterans to protecting our water supply. Please visit my website at www.BolickforArizona.com to learn more or ask questions, and I humbly ask for your vote. Thank you! Shawnna
A36: Cody Reim | B36: Republican | C36: State Representative - District 3 | D36: 3 | E36: Legislative | F36: House | G36: 40 | J36: no statement | K36: =IF(I36="","no statement",IF(I36>0.5,"Yes","No")) -> no statement | L36: (none submitted)
A37: George Khalaf | B37: Republican | C37: State Representative - District 3 | D37: 3 | E37: Legislative | F37: House | G37: 39 | H37: 199 | I37: 0 | J37: Human | K37: =IF(I37="","no statement",IF(I37>0.5,"Yes","No")) -> No | L37: I’m George Khalaf and I’m proud to be running to represent LD3 in the Arizona House. We need leaders to cast and deliver a conservative vision for our state, and that’s why I stepped up. First and foremost, I’m a Christian, husband to Briana, father to three sons and an America-First conservative. My parents immigrated legally to the US from Lebanon to give their children a chance to experience freedom and the American dream. I wake up every day grateful to live in the greatest country in the world. I’ll focus on growing a pro-family economy through low taxes, more efficient government, and pro-small business policies. I’ll support strong families by defending parents’ rights, opposing woke indoctrination and making education work for parents and students. Safe communities start with a secure border. I’ll back our men and women in law enforcement and vote for policies that keep criminals off our streets. I’ll defend our Constitutional Freedoms of life, free speech, religious freedom and the 2nd Amendment. I’ll fight for free and fair elections with full transparency. As your representative, I'll answer to the people and my principles–not special interests. Together, we’ll make Arizona’s next 10 years free and prosperous.
A38: John Skirbst | B38: No Labels | C38: State Representative - District 3 | D38: 3 | E38: Legislative | F38: House | G38: 40 | H38: 157 | I38: 0 | J38: Human | K38: =IF(I38="","no statement",IF(I38>0.5,"Yes","No")) -> No | L38: A moderate and independent voice. Fiscal conservative and liberal leaning on social issues. A problem solver that can place sound judgement above party politics. Helping to shape and pass bipartisan laws will be a priority. Reinventing the economy for the 21st century and lowering costs for Arizona families. This includes repairing a broken health care system. Ensure a sustainable water supply in Arizona. Solutions include upgrading infrastructure and improving water management and conservation strategies. Securing Arizona’s border and fixing a broken immigration process. This includes investments in technology, staffing, and barriers where they make sense. You have a second amendment right to bear arms. With rights though must come responsibilities. Common sense gun laws can help keep our communities safe. I respect your right, if you oppose abortion. So please respect each woman’s right to choose what is best for her own body and unique circumstances. Please cast one of your two votes for an independent candidate.
A39: Julie Gable | B39: Democratic | C39: State Representative - District 3 | D39: 3 | E39: Legislative | F39: House | G39: 39 | H39: 206 | I39: 1 | J39: AI | K39: =IF(I39="","no statement",IF(I39>0.5,"Yes","No")) -> Yes | L39: I raised my family here. I built a career here. And I've watched our state's challenges become personal ones. As an executive, I led teams through hard decisions with high stakes and real, human consequences. Most recently, as the CEO of a healthcare company with more than 250 employees across multiple campuses, I managed a tight budget that required significant cost-cutting efforts. I led our team through a 30% budget reduction without cutting quality of care. Now, I want to put my real-world experience and steady judgment to work for the community I love. I'm running because Arizona deserves leaders who solve problems instead of just talking about them. That starts with making healthcare more affordable by holding insurance companies accountable, reducing unnecessary administrative burden on healthcare providers, and targeting fraud, waste, and abuse. It also means ensuring technology serves people responsibly, strengthening our public schools, and securing our water future for generations to come. I'm not accepting money from big donors or special interests. As a Clean Elections candidate, I am only accountable to the community I serve. I'm not a career politician. I'm a mom, a business owner, and your neighbor. I'm proven, principled, and pragmatic. And I'd be honored to earn your vote.
A40: Richard "Rick" Robert Spargo | B40: Democratic | C40: State Representative - District 3 | D40: 3 | E40: Legislative | F40: House | G40: 40 | H40: 171 | I40: 1 | J40: AI | K40: =IF(I40="","no statement",IF(I40>0.5,"Yes","No")) -> Yes | L40: I stand for Common Sense and Moderation. You won’t find any extremism here. Our District and Arizona deserve leadership grounded in practicality, not partisanship. The challenges we face are water scarcity, underfunded public schools and the rising cost of living. I call for cooperation and real solutions that bring people together, not drive us apart. Securing our water future must be a top priority. We must invest in conservation, expand water reuse, and protect our supplies from overuse and speculation. Arizona can grow while preserving sustainability. Strong public education is the foundation of opportunity. I’ll work to ensure every classroom has the teachers, resources and support needed to help students thrive. Affordability matters. From housing to energy to healthcare. I will champion for policies that keep Arizona livable for working families, small business owners and seniors alike. I’m running to restore moderation and respect to our politics, focusing on results over ideology, collaboration over conflict, and responsibility over division. Together, we can build a balanced, forward-looking future rooted in common sense.
A41: Jeffrey Fortney | B41: Democratic | C41: State Senator - District 3 | D41: 3 | E41: Legislative | F41: Senate | G41: 38 | H41: 197 | I41: 0 | J41: Human | K41: =IF(I41="","no statement",IF(I41>0.5,"Yes","No")) -> No | L41: I am running for State Senate in Legislative District 3 for several reasons. Too many families in Legislative District 3 are feeling the economic impact of decisions being made federally and rubber stamped locally. Many are trying to balance working (sometimes multiple jobs), while paying for child care, medicine and other increasing costly expenses. These people are feeling the effects of national economic decisions locally, while local legislators rubber stamp policies that are driving up these costs. Families are effectively being billed an average of $2,300 due to illegal tariffs. Grocery prices continue to climb while local legislators are doing nothing to support working families. They are in fact making it even more difficult for working families to feed and support their children. I will work tirelessly to support working families in Arizona. In addition, I have a long record of protecting, supporting, and respecting vulnerable children while many local legislators bully these same children while supporting and protecting powerful people who are taking advantage of children. Voters are looking for leadership that prioritizes lowering everyday costs and holding decision-makers accountable for policies that hurt American families. I want to be their advocate at the state capitol.
A42: John Kavanagh | B42: Republican | C42: State Senator - District 3 | D42: 3 | E42: Legislative | F42: Senate | G42: 38 | H42: 174 | I42: 1 | J42: AI | K42: =IF(I42="","no statement",IF(I42>0.5,"Yes","No")) -> Yes | L42: I am running for re-election because Arizona deserves experienced, steady leadership that delivers results. Throughout my legislative service, I have worked to protect our communities, strengthen public safety, and ensure government remains accountable to the people. With a background in law enforcement and years of legislative experience, I understand the challenges facing our state and the practical solutions needed to address them. I have fought to secure Arizona’s borders, support law enforcement, and keep our neighborhoods safe. I believe in responsible government, keeping taxes low, controlling spending, and reducing unnecessary regulations so families and businesses can thrive. Arizona’s continued success depends on affordability and economic growth that protects taxpayers. I am also committed to defending Arizona’s water resources, defending school choice, and keeping "woke" ideologies out of our schools - classrooms should focus on academics, not politics. Additionally, I have supported improvements in transportation infrastructure and investments in education. There is still important work to be done. I ask for your support to continue delivering commonsense leadership to keep Arizona safe, prosperous, and free.
A43: Karen Gresham | B43: Democratic | C43: State Representative - District 4 | D43: 4 | E43: Legislative | F43: House | G43: 43 | H43: 182 | I43: 0 | J43: Human | K43: =IF(I43="","no statement",IF(I43>0.5,"Yes","No")) -> No | L43: As a school board member, she oversees multimillion-dollar budgets, advocates for responsible fiscal management, and supports educators and staff. This gives her the skills and experience needed to carefully evaluate policy for their impact on the public while collaborating with fellow board members. If elected to the legislature, Karen will work for public education funding, fiscal accountability, and an affordable Arizona with a budget that works for everyone. I’m a third-generation Arizonan who believes our state works best when we invest in opportunity and manage our finances responsibly. As a former CPA and graduate of Arizona State University, I understand how to build balanced budgets and analyze data to make smart decisions. I am currently serving my second term as an elected member of the Madison Elementary School District governing board. I know what Arizona schools, teachers, and students need. I am running to strengthen public education, restore fiscal accountability, and ensure an affordable Arizona with a budget that works for everyone. I look forward to representing LD4 in the State House and working on sensible solutions to the challenges we face.
A44: Matt Gress | B44: Republican | C44: State Representative - District 4 | D44: 4 | E44: Legislative | F44: House | G44: 43 | H44: 197 | I44: 0.58558559 | J44: Mixed | K44: =IF(I44="","no statement",IF(I44>0.5,"Yes","No")) -> Yes | L44: Matt Gress represents District 4 in the Arizona House of Representatives, delivering real results for Arizona families. A conservative Republican, Matt believes in securing our border, cutting taxes, balancing budgets, and protecting individual liberty. At the Capitol, Matt has proven he can get things done. He authored and passed the most comprehensive school safety legislation in decades, led the effort to enact Preston’s Law to crack down on teen mob violence, and secured funding to support law enforcement families and strengthen recruitment. He has worked to increase teacher pay, lower the cost of living, and keep Arizona free, competitive, and open for opportunity. Matt’s story is rooted in hard work. Raised by a single mom in a small town in Oklahoma, he worked his way through college by driving school buses and became the first in his family to earn a degree. He later taught high school and served on a local school board, fighting to keep schools open during COVID-19 and expand educational freedom. Before the Legislature, Matt served as Arizona’s budget director, helping deliver the largest tax cut in state history. Matt Gress is a proven conservative fighting to keep Arizona on the right track.
A45: Pamela Carter | B45: Republican | C45: State Representative - District 4 | D45: 4 | E45: Legislative | F45: House | G45: 42 | H45: 188 | I45: 1 | J45: AI | K45: =IF(I45="","no statement",IF(I45>0.5,"Yes","No")) -> Yes | L45: Pamela Carter — Arizona House of Representatives, Legislative District 4 Republican | Candidate for Reelection My name is Pamela Carter. I'm a fourth-generation Arizonan, small business owner, and proud representative of the community I've called home my entire life. In my first term, I was appointed Vice Chair of the Public Safety and Law Enforcement Committee, a leadership role rarely given to a freshman, and I worked to earn it. I passed legislation protecting deployed military service members from unfair vehicle taxes, championed Arizona's nuclear energy future, and stood against powerful corporate interests to defend Scottsdale's right to vote on its own development decisions. This session, I sponsored Cade's Law to hold accountable those who encourage minors toward suicide online, legislation targeting sexual extortion of minors, and bills protecting Arizona homebuyers and expanding access to our state's critical minerals. My priorities haven't changed: safe communities, strong law enforcement, parental rights in education, local control, low taxes, and secure elections. LD4 deserves a representative who shows up, listens, and puts Arizona first. That is the commitment I make to you every day. I humbly ask for your vote. pamelacarter.com
A46: Tammy Caputi | B46: Democratic | C46: State Representative - District 4 | D46: 4 | E46: Legislative | F46: House | G46: 42 | H46: 199 | I46: 1 | J46: AI | K46: =IF(I46="","no statement",IF(I46>0.5,"Yes","No")) -> Yes | L46: I’m Tammy Caputi, and I’m running for the Arizona House of Representatives because Arizona needs leaders who know how to create jobs, balance budgets, and deliver results—not just talk about them. For decades, I've signed the front of paychecks, not the back, and that's the perspective I'll bring to the Legislature. As a small business owner, every payroll represents families who depend on the decisions I make. I've navigated economic uncertainty, rising costs, and tough challenges while keeping people employed and growing a successful business. That experience taught me that leadership means solving problems, making difficult decisions, and being accountable for the results. As a Scottsdale City Councilmember, I worked across the aisle to keep taxes low, invest in infrastructure, strengthen public safety, protect our water future, and deliver practical solutions for our community. If elected, I will fight to keep Arizona affordable, support small businesses, strengthen our education systems, protect taxpayers, and create more opportunity for working families. Too many politicians have spent their careers making promises. I have spent mine making payroll. I will bring that same accountability, common sense, and results-driven leadership to the Arizona House of Representatives. I humbly ask for your vote and trust.
A47: Aaron Lieberman | B47: Democratic | C47: State Senator - District 4 | D47: 4 | E47: Legislative | F47: Senate | G47: 41 | H47: 185 | I47: 1 | J47: AI | K47: =IF(I47="","no statement",IF(I47>0.5,"Yes","No")) -> Yes | L47: Aaron Lieberman is running to deliver practical, results-driven leadership for Arizona families, focused on tackling the state’s affordability crisis, strengthening public education, and building an economy that works for everyone. If elected, Aaron will work to lower everyday costs, address rising housing prices, and expand access to affordable healthcare so families don’t have to choose between paying bills and getting care. He will increase teacher pay and invest in neighborhood public schools to ensure every child has the opportunity to succeed. Aaron is committed to supporting small businesses, creating pathways to good-paying jobs, and growing a strong, sustainable economy. He will also focus on keeping communities safe by supporting law enforcement and ensuring first responders have the resources they need to do their jobs, while protecting Arizona’s water future through responsible, long-term planning. Aaron believes government should deliver real solutions to the problems Arizona families are facing. Aaron has a proven record of working across the aisle to pass meaningful legislation and will continue that approach to deliver results. His goal is simple: make Arizona a place where every family has the opportunity to succeed.
A48: Carine Werner | B48: Republican | C48: State Senator - District 4 | D48: 4 | E48: Legislative | F48: Senate | G48: 41 | H48: 192 | I48: 0 | J48: Human | K48: =IF(I48="","no statement",IF(I48>0.5,"Yes","No")) -> No | L48: As a mom of three Scottsdale public school graduates, I have championed educational excellence and commonsense solutions to the challenges facing our state. In the State Senate, I have fought to keep our children safe, supported small business owners, voted to reduce your taxes, and funded law enforcement. As Senate Health Chair, I have made it a priority to streamline government agencies, improve transparency, and expose waste, fraud, and abuse. The issues facing Arizona are not partisan, which is why I’ve worked across the aisle to improve care for foster children, protect vulnerable Arizonans, and make government programs more effective. Together, we delivered one of the largest tax cuts in state history. I’m proud to have almost two dozen bipartisan bills signed into law in my first term - but our work isn’t done yet. We need proven leadership and elected officials who will tackle critical issues while staying true to the people they represent. I will fight to protect the community we love, secure our water, lower costs, and create new opportunities for the next generation. I am grateful for your support and encouragement. Learn more and get involved at www.wernerforaz.com.
A49: Aaron Marquez | B49: Democratic | C49: State Representative - District 5 | D49: 5 | E49: Legislative | F49: House | G49: 45 | J49: no statement | K49: =IF(I49="","no statement",IF(I49>0.5,"Yes","No")) -> no statement | L49: (none submitted)
A50: Sarah Liguori | B50: Democratic | C50: State Representative - District 5 | D50: 5 | E50: Legislative | F50: House | G50: 45 | H50: 114 | I50: 1 | J50: AI | K50: =IF(I50="","no statement",IF(I50>0.5,"Yes","No")) -> Yes | L50: I’m running to use thoughtful policy and meaningful advocacy to improve people’s lives. I believe government should remove structural barriers, expand opportunity, and focus on the issues that matter most for people, like affordability, access to care, good paying jobs, and safe communities. In the Legislature, I’ve successfully worked to protect reproductive rights, expand housing options, and advance water and environmental solutions that secure our future. As a mom, these issues are personal. I’m focused on building a state where families can thrive, public education is strong, and our kids are prepared for the workforce of tomorrow. My approach is grounded in listening, building relationships, and working collaboratively to deliver real results for Arizona.
A51: Christine Marsh | B51: Democratic | C51: State Senator - District 5 | D51: 5 | E51: Legislative | F51: Senate | G51: 44 | H51: 197 | I51: 0 | J51: Human | K51: =IF(I51="","no statement",IF(I51>0.5,"Yes","No")) -> No | L51: I was first elected to the State Senate in 2020 and served two terms. I have a record of supporting reproductive rights, gun safety, voter protection, clean air, safe water, and education. I originally ran for office because I knew I could be a voice for public-school students, teachers, and staff. As a former English teacher with as many as 44 students in a class, I know what it means to be underfunded and understaffed—and I still do; my teaching experiences guided my work as a member of the Education Committee. I also served on the Transportation Committee where I advocated for public transit and investments in transportation infrastructure. One party rule has stifled Arizona and harmed vulnerable populations. Too many good bills fail without a hearing and it is too easy for extreme legislation to pass with just partisan support. I was able to sponsor and pass a bill to legalize fentanyl testing strips after losing my youngest son to an accidental overdose, but there is more work to be done to mitigate the loss of life due to Arizona’s drug crisis—and I will continue to focus on reducing access to fentanyl and other dangerous drugs.
A52: Jason LaForest | B52: No Labels | C52: State Senator - District 5 | D52: 5 | E52: Legislative | F52: Senate | G52: 44 | H52: 197 | I52: 0 | J52: Human | K52: =IF(I52="","no statement",IF(I52>0.5,"Yes","No")) -> No | L52: Serving as Chief Financial Officer for the Corporation Commission, the Department of Gaming, and the Arizona State Hospital, I witnessed firsthand systemic failures in oversight, accountability, and governance across Arizona’s public institutions. These experiences shaped a core belief: when Arizonans aren’t getting results, the solution isn’t to blame the processes at the bottom, it’s to reform systems at top. I’m running to restore professionalism, strengthen accountability, and return rules-based governance to state government. By modernizing oversight and reinforcing legislative accountability, we can reverse institutional decline and rebuild a public service that delivers for every Arizonan. Government reform motivated me to run for office, but my campaign is about more. As a Clean Elections Candidate, I will work to remove corporate money and influence from political campaigns. Arizona’s initiative, referendum, and recall processes, along with vote by mail, are cornerstones of our democracy; they must be protected, and expanded in ways that meet today's voters. Above all, as an independent, I am committed to effectively representing Central Phoenix as State Senator for LD5. If you are in this district, I want to hear from you. Please visit my website and share the issues that matter most to you.
A53: Brendan Trachsel | B53: Green | C53: State Representative - District 6 | D53: 6 | E53: Legislative | F53: House | G53: 48 | H53: 195 | I53: 1 | J53: AI | K53: =IF(I53="","no statement",IF(I53>0.5,"Yes","No")) -> Yes | L53: Brendan Trachsel believes government is supposed to work for people, not donors or party leaders. That belief is why he's running for State Representative in Legislative District 6 as a Green, free from corporate pressures that shape what both major parties are willing to fight for. Brendan earned a B.S. in Parks and Recreation Management and an M.Ed. in Counseling - Student Affairs from Northern Arizona University, and spent years organizing in Flagstaff. After nine months of coalition advocacy, he pushed the city to cancel its Flock Safety surveillance contract. That's the kind of work he brings to the legislature. Arizona is being sold to the tech industry. AI data centers are draining our water, straining our grid, and being waved through with little public input. Brendan will fight for a statewide moratorium and people-centered regulations that put communities before corporations. His other priorities are straightforward: collective bargaining for all, full funding for public schools, strong privacy protections, and a democracy free from dark money. Brendan answers only to the people of LD6. At 25 years old, he's part of a generation that grew up watching institutions fail and decided to do something about it.
A54: Ian Teller | B54: Democratic | C54: State Representative - District 6 | D54: 6 | E54: Legislative | F54: House | G54: 47 | H54: 194 | I54: 1 | J54: AI | K54: =IF(I54="","no statement",IF(I54>0.5,"Yes","No")) -> Yes | L54: Ian Teller is running for State Representative in Legislative District 6 to bring bold, community- centered leadership to Northern Arizona. Rooted in his Diné upbringing, Ian believes in building a future where families are supported, communities are connected, and no one is left behind. His priorities begin with strengthening public education by ensuring schools are fully funded, culturally responsive, and accessible to every child—because no student should feel unsafe or unable to learn due to financial hardship. Ian is also focused on addressing the housing crisis by advancing smart housing solutions that build communities, not just homes, with infrastructure that supports long-term growth in rural and Tribal areas. He is committed to tackling the rising cost of living by supporting policies that improve affordability for working families. Protecting the environment and securing water rights are central to Ian’s vision. He is committed to safeguarding natural resources for future generations while promoting sustainable development. Ian is running a people-powered campaign, rejecting corporate and special interest money to remain accountable only to the people of LD6. Through collaboration, transparency, and respect for community voices, Ian Teller is ready to serve and deliver meaningful change for Arizona.
A55: Mae Peshlakai | B55: Democratic | C55: State Representative - District 6 | D55: 6 | E55: Legislative | F55: House | G55: 47 | H55: 193 | I55: 0 | J55: Human | K55: =IF(I55="","no statement",IF(I55>0.5,"Yes","No")) -> No | L55: Representative Mae Peshlakai is Diné - Tangle People Clan and born for the Deer Water Clan, maternal grandfathers are of the Salt clan and paternal grandfathers are of the Rock Gap clan. She is a boarding school survivor. Mae attended a U.S. Federal Bureau of Indian Affairs Boarding School in Tolani Lake, Arizona, 100 miles northeast of Flagstaff, Arizona.. Mae was married to James Peshlakai, an accomplished silver and goldsmith. She took up silversmithing and, to this day, makes jewelry every day as well as weaves. She and her husband worked with prestigious colleges and universities across the nation sharing the Navajo culture and assisting scholarly research. Mae knows the issues and challenges of District 6 and has worked tirelessly for two terms representing all the communities of District 6. In 2025, Representative Peshlakai fought and voted for a budget that made historic investments in Indigenous Tribal healthcare and traditional healing practices. Rep. Peshlakai was elated to support an opportunity to leverage $100,000 from the state to secure more than $220 million in federal matching funds to cover culturally relevant traditional healing practices that are vital to our way of life and well-being.
A56: Jamescita Peshlakai | B56: Democratic | C56: State Senator - District 6 | D56: 6 | E56: Legislative | F56: Senate | G56: 46 | H56: 140 | I56: 0 | J56: Human | K56: =IF(I56="","no statement",IF(I56>0.5,"Yes","No")) -> No | L56: I am Navajo of the Tangle People Clan, born for the Red House clan, maternal grandfathers are of the Deer Water clan, and paternal grandfathers are of the Cliff Dweller clan. I was born north of the sacred mountain of the west, Doo'ko'osliid (the San Francisco Peaks). Funding public education, providing for our youth and elders, and protecting the environment will be key tenants of my service at the legislature. Tribal sovereignty must be respected and being LD 6 this district represents 10 tribes in Arizona, it's vital that we elect a representative who can work with these tribes and advance their interests at the state legislature. We are the largest, most rural district in the state and we deserve representation that will travel to meet people where they are at. I am committed to serving the people of Arizona.
A57: Lloyd Johnson | B57: Republican | C57: State Senator - District 6 | D57: 6 | E57: Legislative | F57: Senate | G57: 46 | H57: 214 | I57: 1 | J57: AI | K57: =IF(I57="","no statement",IF(I57>0.5,"Yes","No")) -> Yes | L57: I am not a politician, I am a Statesman. A "statesman" and a "politician" are both individuals involved in public affairs, but they are often distinguished by their motivations and perceived impact. A statesman is generally viewed as someone who prioritizes the long-term well-being and interests of their nation or community, often acting with integrity and statesmanship. In contrast, a politician is often perceived as someone primarily driven by personal ambition, electoral success, or party interests, potentially at the expense of broader public good. Here's a more detailed breakdown: Statesman: Focus: Long-term public good, national interests, and ethical principles. Actions: Guided by a sense of responsibility, integrity, and a desire to leave a positive legacy. Perception: Often viewed with respect and admiration for their wisdom and leadership. Example: Figures like George Washington are often cited as examples of statesmen. Politician: Focus: Electoral success, party loyalty, and personal advancement. Actions: May prioritize short-term gains, compromise on principles for political expediency, or engage in tactics that are seen as self-serving. Perception: Can be viewed with skepticism or distrust, particularly if their actions are perceived as opportunistic or self-serving. In essence, while both statesmen and politicians operate within the same sphere of public life, the distinction lies in their motivations, priorities, and the perceived impact of actions.
A58: David Cook Sr. | B58: Republican | C58: State Representative - District 7 | D58: 7 | E58: Legislative | F58: House | G58: 50 | H58: 166 | I58: 0 | J58: Human | K58: =IF(I58="","no statement",IF(I58>0.5,"Yes","No")) -> No | L58: I’m a work horse whose rural roots are deep and real. I’m a rancher and state leader on issues related to water, agriculture, ranching, and more. My record is 100% pro-Taxpayer, pro-2nd Amendment, pro-Life, and pro -Constitution. I’ve delivered college and K-12 funding for our classrooms and teachers, I’ve championed real election integrity measures, pushed to secure our borders and enforce our laws, and brought funding to our district to improve our roads, highways and bridges. Payson, Globe, Florence, Williams, Heber, Show Low, Snowflake or Pinetop-Lakeside aren’t just places on a map, they’re my towns and people. I support President Trump’s fight against the DC swamp and ran the bill to Term Limit Congress. I’m running as a team with Walt Blackman because we share conservative values, we both fight for rural Arizona, and I appreciate his service to our nation and the integrity he brings to the job. You get TWO VOTES for State House, so please vote David Cook AND Walt Blackman. Thank you!
A59: Richard Grayson | B59: Green | C59: State Representative - District 7 | D59: 7 | E59: Legislative | F59: House | G59: 51 | H59: 200 | I59: 0 | J59: Human | K59: =IF(I59="","no statement",IF(I59>0.5,"Yes","No")) -> No | L59: I have been active in Democratic politics since 1964, when at 13 I handed out leaflets on a street corner near my Brooklyn home reading "Get on the Johnson, Humphrey, Kennedy Team" – strategically linking Bobby Kennedy's high-profile, out-of-state Senate bid to the popular Johnson-Humphrey ticket. This year I'm asking LD7 Democratic voters to look past my pro forma Green Party designation, because I am a member of the "Hobbs, Fontes, Mayes, Mike Montiel, Sam Martin, et al. Democratic Team." Between 1994 and 2004, I ran as a write-in candidate against three Republican U.S. House members from Florida when no Democrat was on the ballot, and did the same against unopposed Arizona Rep. Paul Gosar in 2022. In 2014, I was the Democratic nominee for Wyoming's lone Congressional seat and won Teton County when the nominees for governor and senator were losing it. I am anti-Trump, anti-MAGA, and antiwar. I took part in local No Kings and ICE-Out demonstrations, and worked in the campaigns of George McGovern, Bill Clinton, John Kerry, Barack Obama, and other Democrats. In the highly unlikely event a progressive like me is elected to the Arizona legislature, I would, of course, join the Democratic majority caucus.
A60: Samuel "Sam" Martin | B60: Democratic | C60: State Representative - District 7 | D60: 7 | E60: Legislative | F60: House | G60: 51 | H60: 115 | I60: 0 | J60: Human | K60: =IF(I60="","no statement",IF(I60>0.5,"Yes","No")) -> No | L60: This year, it's important to make the right choice for legislator. I'm the right choice for LD7: I know the real pitfalls and potential of technologies like social media and AI - my opponents will believe any salesman who walks in the door. I will ensure healthcare access for every Arizonan - my opponents will let you die in a gutter. I know the value of good public schools because I went to them - my opponents will never do anything for public education but tear it down. I am the only candidate who will stand up the the corruption, cruelty, and chaos coming from Washington DC. The choice is clear - vote for Sam!
A61: Walter "Walt" Blackman | B61: Republican | C61: State Representative - District 7 | D61: 7 | E61: Legislative | F61: House | G61: 50 | H61: 176 | I61: 0 | J61: Human | K61: =IF(I61="","no statement",IF(I61>0.5,"Yes","No")) -> No | L61: As a veteran, I don’t use words like honor casually. So when I tell you that I’m honored to serve as your State Representative, please know how sincerely I mean it. I campaign as an Arizona First conservative and then I govern just like I said I would. That means I’m working hard on advancing our shared goals: A strong rural economy, quality schools and school choice, secure borders and secure elections, medical freedom, religious liberty, low taxes, rural infrastructure, protecting our water, passing Term Limits on Congress, protecting our Constitutional rights, and much more. I’m running as a team with David Cook because he has a very strong record of championing rural Arizona’s needs, and I believe we’ll be a dynamic and effective team. I’m a proud combat veteran who believes in the greatness of America, if we fight to defend it. I ask for your vote and thank you for the trust you have placed in me. You get TWO VOTES for State House, so please vote Walt Blackman AND David Cook. Thank you!
... A183: Leo Biasiucci | B183: Republican | C183: State Senator - District 30 | D183: 30 | E183: Legislative | F183: Senate | G183: 118 | H183: 185 | I183: 0 | J183: Human | K183: =IF(I183="","no statement",IF(I183>0.5,"Yes","No")) -> No | L183: Too many politicians run for office making promises they never keep. Over my eight years in office, I’ve done the opposite. I’ve followed through and delivered while protecting our conservative values. I made Arizona a Second Amendment sanctuary state. I fought to impose life sentences for child sex crimes. I removed toxic food dyes and chemicals from our schools. I empowered law enforcement to arrest and prosecute human smugglers. I supported a flat income tax and worked to prevent government overreach by banning the shutdown of businesses during a pandemic. And when our communities needed results, I got them. When Lake Havasu and Bullhead City needed Highway 95 repaved, I made it happen. When Wickenburg needed funding for its fire station, I secured it. When the Mohave County Sheriff’s Department needed to replace 40+ year-old substations, I delivered. When Kingman needed a bypass at Highway 93/I-11 and Beale Street, I got it done. When Lake Havasu needed a second bridge, I made it happen. I’m proudly Pro-Life, Pro-Second Amendment, Pro- Veterans, Pro-Law Enforcement, Pro-Border Security, and Pro-America First. Visit Leobiasiucci.com to help keep Arizona red.
A184: Jasmine Blackwater-Nygren | B184: Democratic | C184: Apache Attorney | E184: County | G184: 121 | J184: no statement | K184: =IF(I184="","no statement",IF(I184>0.5,"Yes","No")) -> no statement | L184: (none submitted)
A185: Samceita Begay | B185: Democratic | C185: Apache Clerk Of The Superior Court | E185: County | G185: 122 | H185: 193 | I185: 0 | J185: Human | K185: =IF(I185="","no statement",IF(I185>0.5,"Yes","No")) -> No | L185: I am currently part of the Navajo Housing Authority where I have the privilege of serving my Dine families with their homes. Being fluent in Navajo has helped drive my passion for serving others and our mission for helping families. My journey with the organization began 17 years ago when I first joined as a Resident Intake Officer. Over the years, I have been actively involved in community events which have deepened my understanding and commitment to our community. If elected, my primary goals are to educate the role of the Clerk of the Superior Court as well as introducing new services across the county. I believe that by focusing on education, we can achieve significant progress for years to come. My knowledge around policy will help me guide our constituents with any court proceedings and/or services. Thank you for considering my candidacy. I am excited about the opportunity to serve as your Apache County Clerk of the Superior Court and to work together towards a prosperous future, together. I look forward to the possibility of contributing my skills and passion to our shared success. Thank you for your time and consideration. Ahe’hee
A186: Amy Hunley | B186: Republican | C186: Cochise Clerk Of The Superior Court | E186: County | G186: 124 | H186: 102 | I186: 1 | J186: AI | K186: =IF(I186="","no statement",IF(I186>0.5,"Yes","No")) -> Yes | L186: During my two terms as Clerk, I have focused on strengthening my office through improved efficiency, accountability, and customer service. I have prioritized staff retention and development by increasing salaries, expanding training opportunities, and implementing clear, consistent procedures. These efforts have created a more stable, knowledgeable workforce that delivers reliable and timely service. I have also advanced the office’s use of technology to improve accuracy, streamline operations, and increase access to court services. There is important work still ahead. I remain committed to continuing this progress, strengthening partnerships within the justice system, and serving Cochise County with professionalism, integrity, and proven leadership.
A187: Billy Cloud | B187: Republican | C187: Cochise Recorder | E187: County | G187: 123 | H187: 185 | I187: 1 | J187: AI | K187: =IF(I187="","no statement",IF(I187>0.5,"Yes","No")) -> Yes | L187: Billy A. Cloud possesses the experience, leadership, and technical knowledge necessary to effectively continue the work of the Cochise County Recorder’s Office. His background includes senior management roles in the Cochise County Superior Court, the Arizona House of Representatives, and the Arizona Department of Economic Security, where he has overseen large-scale operations, supervised staff, and ensured compliance with complex legal and regulatory frameworks. Cloud has extensive experience managing records, including leading a multi-year court records archiving project in coordination with the State Library and Archives. His career demonstrates a consistent ability to implement process improvements, maintain accurate documentation, and ensure transparency and accountability—core functions of the Recorder’s Office. He is well-versed in Arizona statutes and understands the legal requirements surrounding public records, voter registration, and document recording. In addition, Cloud has managed multimillion-dollar budgets, developed policy, and worked closely with elected officials, stakeholders, and the public. His leadership style emphasizes organization, accuracy, and responsiveness. With a strong commitment to public trust, operational efficiency, and modernizing systems where appropriate, Cloud is prepared to ensure the Recorder’s Office continues to serve Cochise County with professionalism and integrity.
A188: Bradley Crossland | B188: Democratic | C188: Coconino Clerk Of The Superior Court | E188: County | G188: 125 | H188: 86 | I188: 0.58434784 | J188: Mixed | K188: =IF(I188="","no statement",IF(I188>0.5,"Yes","No")) -> Yes | L188: I care deeply about our justice system and the role the Clerk’s Office plays in ensuring it functions effectively. I also want to help educate voters about the importance of local offices and what the Clerk of Superior Court actually does. My current priorities include improving customer service, reducing backlogs, expanding paperless operations, implementing digital evidence systems, and launching a new jury management platform. I also support expanding rural court access through programs like the Justice Bus and using technology to bring services closer to residents.
A189: Anita Escobedo | B189: Democratic | C189: Gila Clerk Of The Superior Court | E189: County | G189: 127 | H189: 199 | I189: 1 | J189: AI | K189: =IF(I189="","no statement",IF(I189>0.5,"Yes","No")) -> Yes | L189: With 24 years of dedicated service as Clerk of the Court, my vision is to continue building an office environment that serves our community with integrity, transparency, and excellence. I have spent my career ensuring that the Gila County Clerk of Court office operates efficiently, accurately, and with the highest level of professionalism. Moving forward, I am committed to strengthening public trust by making court services more accessible, embracing technology that improves efficiency, and maintaining clear, open communication with the public. A key priority is expanding and promoting access to justice, ensuring every member of our community can navigate the court system with clarity, fairness, and confidence. I believe the Clerk’s Office should be a place where every individual is treated with respect and every case is handled with care. My experience has prepared me to lead with knowledge, stability, and a deep understanding of the evolving needs of our courts and community. I will continue to support and develop our dedicated team, improve processes, and ensure we meet the highest standards of service. Together, we can build on a strong foundation and move confidently into the future providing reliable, responsive, and trusted service to every person we serve.
A190: Yvette Hoffman | B190: Independent | C190: Gila Clerk Of The Superior Court | E190: County | G190: 127 | H190: 118 | I190: 1 | J190: AI | K190: =IF(I190="","no statement",IF(I190>0.5,"Yes","No")) -> Yes | L190: Why I'm Running: If someone had told me a few years ago that I'd be running for public office, I probably wouldn't have believed them. But sometimes life has a way of leading us where we're meant to be. I'm running as an Independent because the Clerk's Office is a nonpartisan position, and I believe it should serve everyone fairly. The Clerk's Office isn't about politics—it's about people. It's a role focused on records, processes, and public service, maintaining that balance is essential. I hope to build on a strong foundation by honoring tradition while embracing practical technology that improves service and strengthens the connection between our court locations. To me, that's what public service is all about.
A191: Wendy Mannigel-Smith | B191: Republican | C191: Gila Recorder | E191: County | G191: 126 | H191: 200 | I191: 0 | J191: Human | K191: =IF(I191="","no statement",IF(I191>0.5,"Yes","No")) -> No | L191: I appreciate the confidence the Gila County Board of Supervisors placed in me when they unanimously appointed me as Gila County Recorder in 2025. I am now running to be elected to the office of Gila County Recorder to continue the work that I have been doing and continue building and educating our team to serve Gila County along with the modernization of the Recorder’s Office. Voting is a treasured fundamental right for American citizens. I will do everything in my authority to ensure secure, transparent, legal and fair election processes while maintaining accurate voter registration records. I have called on our communities to assist in communicating accurate information, to help educate with factual verified data to increase Gila County’s participation and faith in the electoral process. Increased transparency and public engagement in the electoral process enhances confidence in the integrity of the system. Regardless of political party affiliation I am approachable, available, and welcome opportunities to engage in our communities. I believe that increased accessibility allows me to address voter concerns effectively and build trust to dispel misconceptions of the processes. Please cast your vote for Wendy Mannigel-Smith as Gila County Recorder, serving our community is truly my privilege.
A192: Heidi Torrio | B192: Republican | C192: Graham Clerk Of The Superior Court | E192: County | G192: 128 | H192: 186 | I192: 0 | J192: Human | K192: =IF(I192="","no statement",IF(I192>0.5,"Yes","No")) -> No | L192: The Clerk of the Superior Court serves as the Court’s official record keeper. The mission of the Graham County Clerk’s Office is to provide fair, impartial and efficient customer service to the public without giving improper and/or legal advice. We are the point of contact into the judicial system for the public to access the court process. While serving as the Clerk for Graham County, I have focused on cross training my staff to give them the skills they need to ensure our office runs smoothly while providing excellent customer service. Our staff is committed to efficiency, accuracy and accountability while maintaining court records. New technology has been implemented to improve our operating systems to provide the public with better access to the courts. As I continue serving Graham County in the role of Clerk, I envision an office dedicated to providing access to our justice system. I will continue to build trust and confidence in the courts through the continued guidance and training of court staff to meet the needs of the public. I appreciate your support and vote in the upcoming elections. Thank you!
A193: Madeline Montoya | B193: Democratic | C193: Greenlee Clerk Of The Superior Court | E193: County | G193: 129 | J193: no statement | K193: =IF(I193="","no statement",IF(I193>0.5,"Yes","No")) -> no statement | L193: (none submitted)
A194: Kari Ann Noeltner | B194: Republican | C194: La Paz Assessor | E194: County | G194: 130 | H194: 201 | I194: 1 | J194: AI | K194: =IF(I194="","no statement",IF(I194>0.5,"Yes","No")) -> Yes | L194: Her volunteer efforts reflect a dedication to creating opportunities for youth, honoring those who have served, and strengthening connections within the community. With deep local ties and a practical, hands- on approach, she remains committed to serving both inside and outside of her role in county government. I am running for La Paz County Assessor to continue providing stable, experienced leadership following my appointment to fill the vacancy created by the early retirement of our previous Assessor. I previously served as Chief Deputy Assessor and stepped into this role to ensure continuity while the community prepares to elect its next Assessor in 2026. This election provides voters the opportunity to choose who will lead the office moving forward. The Assessor’s Office plays a critical role in ensuring fair and accurate property valuations. I am committed to carrying out that responsibility with consistency, transparency, and accountability. My experience in the office has given me a strong understanding of both the technical work and the importance of public trust. I have been directly involved in maintaining operations, supporting staff, and continuing improvements that strengthen service to our community. I will continue to focus on fairness, clear communication, and responsible stewardship of this office.
A195: Hollie Lucas | B195: Republican | C195: La Paz Clerk Of The Superior Court | E195: County | G195: 132 | H195: 195 | I195: 0.83220977 | J195: AI | K195: =IF(I195="","no statement",IF(I195>0.5,"Yes","No")) -> Yes | L195: As Clerk of the Superior Court, I am committed to ensuring my office fulfills every responsibility required by Arizona law and the Rules of Court. Our office serves the public by accepting Superior Court filings, maintaining official court records, collecting and distributing court-ordered fines, fees, victim restitution, issuing marriage licenses, and managing jury selections. My priority is providing exceptional public service. I believe every person who enters our office deserves to be treated with dignity, respect, compassion, and professionalism, especially during what is often a difficult time in their lives. Since taking office, I have worked to make the Clerk's Office more efficient, accessible, and customer-focused while maintaining the integrity of our judicial system. I remain actively involved in statewide judicial committees, including the Arizona Commission on Access to Justice, the Judicial Officer Supervisor Training Workgroup, and the Arizona State, Tribal, and Federal Court Forum. These opportunities allow me to collaborate with court professionals across Arizona, stay current on best practices, and bring innovative ideas back to La Paz County. I am proud of what my team and I have accomplished, and I remain committed to serving our community with honesty, transparency, integrity, and dedication.
A196: Lonnie Lewis | B196: Republican | C196: La Paz County School Superintendent | E196: County | G196: 131 | H196: 103 | I196: 1 | J196: AI | K196: =IF(I196="","no statement",IF(I196>0.5,"Yes","No")) -> Yes | L196: Every student in our county deserves opportunity, advocacy, and a voice. As part of the La Paz County Superintendent's Office, I am committed to showing up, listening to every district, and working tirelessly to expand educational opportunities for all youth. Together, we will build stronger schools, stronger districts, and a stronger future for our communities. I envision a united La Paz County where every district is connected, supported, and empowered. By bringing together resources, building strong partnerships, and creating a dependable network of support, the La Paz County Superintendent's Office will help every school create the best possible learning environment for its students.
A197: Jeff Dial | B197: Republican | C197: Maricopa Clerk Of The Superior Court | E197: County | G197: 133 | H197: 196 | I197: 0.53859204 | J197: Mixed | K197: =IF(I197="","no statement",IF(I197>0.5,"Yes","No")) -> Yes | L197: Jeff Dial knows most people never hear about the Clerk's Office until they need it. The office keeps the records for every Superior Court case in Maricopa County, records that guard the integrity of our justice system. It processes child-support payments, delivers victim restitution to families, issues marriage licenses, and helps people through the hardest days of their lives: a divorce, a probate case, a custody matter. When you need it, it should be easy to find, easy to understand, and easy to use. Jeff believes in the power of education. People deserve to know how their courts work. His priorities are clear: educate the public about this office, expand online filing so residents can use its services from anywhere, in any language, and cut red tape so no one needs a lawyer for basic paperwork. The Clerk's Office must stay above politics. Judge candidates for this office by one standard: will they uphold the law and follow the Constitution, not a personal agenda? Integrity matters. Jeff Dial will manage this office by that standard and serve everyone equally. Whatever your politics, Jeff asks for your vote. He will deliver a Clerk's Office that simply works.
A198: Sebastian Seb Maximiliano Matta | B198: Democratic | C198: Maricopa Clerk Of The Superior Court | E198: County | G198: 133 | H198: 199 | I198: 0.49769586 | J198: Mixed | K198: =IF(I198="","no statement",IF(I198>0.5,"Yes","No")) -> No | L198: Seb is running for Maricopa County Clerk of the Superior Court with three main priorities. First, he wants to make the Clerk’s website available in more languages than just English. Many counties already provide multilingual websites so residents can access court records and services regardless of which language they speak. In Maricopa County, where 26% of residents speak a language other than English at home, there is no reason the Clerk’s website should remain English-only. Second, Seb wants to modernize the Clerk’s Office by expanding online systems. For example, probate matters involving wills and estates often still require in-person filing. This creates unnecessary costs and delays for families and legal professionals. Seb believes expanding online filing options would save time, reduce expenses, and make the court system more efficient and accessible. Finally, Seb wants to raise public awareness about what the Clerk’s Office does and why it matters. He hopes to visit schools and community meetings to explain the office’s role in the justice system and encourage greater civic understanding. He especially wants to inspire young people to become engaged in public service, law, and government. Seb is running to make the Clerk’s Office more accessible, modern, and understandable.
A199: Christina Spurlock | B199: Republican | C199: Mohave Clerk Of The Superior Court | E199: County | G199: 134 | H199: 190 | I199: 0.34176183 | J199: Mixed | K199: =IF(I199="","no statement",IF(I199>0.5,"Yes","No")) -> No | L199: My name is Christina Spurlock. I currently serve as and am running for the Clerk of the Superior Court in Mohave County, where I am responsible for supporting the judicial system and providing essential services to the public. As outlined in the Arizona Constitution and state law, my office maintains court records, manages case filings, coordinates jury services, and processes court-related financial transactions. In addition to these duties, I also serve as the Probate Registrar and Jury Commissioner, and I participate in both local and statewide judicial initiatives. I began my service with the Clerk’s Office in 2007, was appointed by Governor Doug Ducey on August 24, 2021, to serve as the Clerk of the Mohave County Superior Court and was elected to my first full term beginning in January 2023. The responsibilities of this office require a detailed understanding of court operations, statutory processes, and the needs of the public. Having extensive experience and professional qualifications helps ensure the accuracy, integrity, and continuity of the services the Clerk’s Office provides. I possess that experience and am passionate about serving my community. I appreciate your vote in the upcoming election.
A200: Michael Sample | B200: Republican | C200: Navajo Clerk Of The Superior Court | E200: County | G200: 135 | J200: no statement | K200: =IF(I200="","no statement",IF(I200>0.5,"Yes","No")) -> no statement | L200: (none submitted)
A201: James Giacomino | B201: Democratic | C201: Pima Clerk Of The Superior Court | E201: County | G201: 137 | H201: 170 | I201: 1 | J201: AI | K201: =IF(I201="","no statement",IF(I201>0.5,"Yes","No")) -> Yes | L201: I’m honored to serve as your Clerk of the Superior Court in Pima County and am proud to be running to continue that service. As a lifelong Arizonan and public servant, I have spent over 15 years working within the Clerk’s office, starting in an entry-level position and rising through the ranks to lead this vital institution. Since my appointment, I have focused on strengthening transparency, improving access to court services, and ensuring our office operates efficiently for the public, attorneys, and judiciary. The Clerk’s office plays a critical role in maintaining the integrity of our justice system—managing records, supporting court operations, and serving our community with professionalism and accountability. I am committed to modernizing services, expanding digital access, and supporting the dedicated staff who keep our courts running every day. My leadership emphasizes innovation, fiscal responsibility, and responsiveness to the needs of Pima County residents. I respectfully ask for your support so I can continue working to ensure our courts remain accessible, efficient, and worthy of the public’s trust.
A202: Rebecca Padilla | B202: Republican | C202: Pinal Clerk Of The Superior Court | E202: County | G202: 138 | J202: no statement | K202: =IF(I202="","no statement",IF(I202>0.5,"Yes","No")) -> no statement | L202: (none submitted)
A203: Juan Pablo Guzman | B203: Democratic | C203: Santa Cruz Clerk Of The Superior Court | E203: County | G203: 140 | J203: no statement | K203: =IF(I203="","no statement",IF(I203>0.5,"Yes","No")) -> no statement | L203: (none submitted)
A204: Maya Donnelly | B204: Democratic | C204: Santa Cruz County School Superintendent | E204: County | G204: 139 | H204: 202 | I204: 0.29632106 | J204: Mixed | K204: =IF(I204="","no statement",IF(I204>0.5,"Yes","No")) -> No | L204: As a candidate for Santa Cruz County School Superintendent, I understand the statutory responsibilities of the office require a qualified leader who prioritizes compliance, transparency, and clear communication. I am committed to upholding these standards while serving as a dependable and collaborative partner to our school communities. My priorities center on being a consistent and knowledgeable support system for educational communities. This means working closely with school leaders to help them achieve their fiscal and instructional goals based on their unique needs. It also means bringing together education stakeholders, community organizations, and business and industry partners to create meaningful, relevant opportunities for learners of all ages. My goals for the office include: Providing quality, reliable services as a fiscal agent for school districts, while maintaining meticulous oversight of budgets, transactions, and reporting; Strengthening support services for schools and teachers that include professional development, grant funding, and county-wide annual events; Expanding post-secondary preparedness and meaningful workforce experience for youth; Supporting student well-being through partnerships that address mental health, prevention, safety, and family engagement. If elected, I aim to foster teamwork, and thoughtful problem-solving. I will build trust through accountability and demonstrate that respect and empathy are at the core of my leadership style.
A205: Charlie Van Landingham | B205: Republican | C205: Yavapai Clerk Of The Superior Court | E205: County | G205: 142 | J205: no statement | K205: =IF(I205="","no statement",IF(I205>0.5,"Yes","No")) -> no statement | L205: (none submitted)
A206: Bobbie Jo Daily | B206: Republican | C206: Yuma Clerk Of The Superior Court | E206: County | G206: 143 | H206: 199 | I206: 1 | J206: AI | K206: =IF(I206="","no statement",IF(I206>0.5,"Yes","No")) -> Yes | L206: I am proud to be a candidate for Clerk of Superior Court in Yuma County, Arizona, bringing 15 years of dedicated service and proven leadership within the Clerk's Office. I began my career in 2011 as a financial clerk, learning the foundation of the office from the ground up. Through hard work, commitment, and a deep respect for public service, I advanced through the ranks to my current role as the Chief Deputy. Today, I am responsible for the day to day operations of the Clerk's Office, overseeing a staff of 49 and preparing and monitoring the office's budget. I have made it a priority to understand every desk, duty, and responsibility, allowing me to support staff, strengthen teamwork, and lead with integrity. I served on the Yuma County Budget Review Team and contributed to projects that modernize and improve efficiency. I am experienced, loyal, and committed to progress. I am ready to take the next step to lead, support the amazing staff, and continue serving Yuma County with transparency, innovation, and dedication. With a career built from the ground up, it would be a seamless transition for me to assume the role of the Clerk of Superior Court.
A207: Marie Moore | B207: Republican | C207: Yavapai Board Of Supervisors Dist. 2 | D207: 2 (Supervisors) | E207: County | G207: 141 | H207: 182 | I207: 1 | J207: AI | K207: =IF(I207="","no statement",IF(I207>0.5,"Yes","No")) -> Yes | L207: I have lived, worked, and raised my family in Yavapai County. I grew up here, went to school here, and never left. My husband and I have built our life here, and like many of you, we care deeply about our children’s and grandchildren’s future. This isn’t something I originally set out to do, but through my time serving our community, I’ve come to see where I can continue to help. I’ve been grateful for the opportunity to serve on Town Council and now as Mayor, while also helping operate a local business that provides jobs and supports our community. Through that experience, I’ve worked through the kinds of challenges our communities face every day. I understand the importance of infrastructure, responsible growth, and the long-term impact land use decisions have on our communities. I’m not a career politician. I’m someone who believes in showing up, listening, and making thoughtful decisions. Yavapai County is growing, and we need to be intentional about how and where that growth happens while protecting the rural character and way of life that make our communities strong.
A208: Andrés Cano | B208: Democratic | C208: Pima Board Of Supervisors Dist. 5 | D208: 5 (Supervisors) | E208: County | G208: 136 | H208: 202 | I208: 1 | J208: AI | K208: =IF(I208="","no statement",IF(I208>0.5,"Yes","No")) -> Yes | L208: I’m Democrat Andrés Cano. I'm running for Pima County Supervisor because I believe county government should improve people’s lives in real and lasting ways. As your Supervisor, I have focused on protecting our neighborhoods, expanding opportunity, and delivering results for working families across District 5. I have worked to advance affordable housing, support early childhood education, protect open space, and strengthen our commitment to public safety and public health. I voted no on Project Blue because I believe we must stand up for our desert, protect our water, and reject development that puts our communities at risk. I have also supported investments in workforce pay, neighborhood infrastructure, and environmental protection. My approach to public service is rooted in the values I learned growing up: work hard, stay grounded, and never forget who you are fighting for. As the product of a single mother and a first-generation college graduate, I know how much leadership and compassion matters when families are trying to get ahead. I’m running to keep building a Pima County that is affordable, safe, and more responsive to the people it serves — from Midtown and Downtown to the West Side, the Southside, and the Pascua Yaqui Nation. Learn more: AndresforSupervisor.com
A209: Jeff Rhodes | B209: Republican | C209: Pima Board Of Supervisors Dist. 5 | D209: 5 (Supervisors) | E209: County | G209: 136 | H209: 195 | I209: 1 | J209: AI | K209: =IF(I209="","no statement",IF(I209>0.5,"Yes","No")) -> Yes | L209: I’m running for Pima County Supervisor because I believe government should work for the people it serves. It should listen, solve problems, operate efficiently, and deliver real results for families and communities. Too often, people feel like they are fighting systems instead of being served by them, and I believe we can do better. Today, I work as a Mortgage Loan Originator right here in District 5. Every day I sit across the table from individuals and families making some of the biggest financial decisions of their lives. I see firsthand the challenges many people are facing, from affordability and housing costs to the pressures working families experience every day. One of my biggest pet peeves is inefficiency. I believe government should focus less on bureaucracy and more on practical solutions. Leadership is not about titles or politics. It’s about listening, finding solutions, and making things work better for the people who depend on them. I’m running because I believe our community deserves leadership that brings real-world experience, common sense, and a commitment to getting things done. I love this community, I believe in its future, and I would be honored to earn your support.

Sheet Summary & charts
A1: Summary Figures
A3: Overall
A4: Statements scored | B4: =COUNT(Candidates!I2:I209) -> 198
A5: Flagged (AI score > 0.50) | B5: =COUNTIF(Candidates!I2:I209,">0.5") -> 70
A6: Flagged rate | B6: =B5/B4 -> 0.35353535
A7: Scored exactly 0.00 | B7: =COUNTIF(Candidates!I2:I209,0) -> 121
A8: Scored 0.95 or higher | B8: =COUNTIF(Candidates!I2:I209,">=0.95") -> 63
A9: Candidates with no statement | B9: =COUNTIF(Candidates!J2:J209,"no statement") -> 10
A13: By race type
B14: Statements | C14: Flagged | D14: Rate
A15: Statewide | B15: =COUNTIFS(Candidates!$E$2:$E$209,$A15,Candidates!$I$2:$I$209,">=0") -> 23 | C15: =COUNTIFS(Candidates!$E$2:$E$209,$A15,Candidates!$I$2:$I$209,">0.5") -> 7 | D15: =IFERROR(C15/B15,0) -> 0.30434783
A16: Legislative | B16: =COUNTIFS(Candidates!$E$2:$E$209,$A16,Candidates!$I$2:$I$209,">=0") -> 155 | C16: =COUNTIFS(Candidates!$E$2:$E$209,$A16,Candidates!$I$2:$I$209,">0.5") -> 49 | D16: =IFERROR(C16/B16,0) -> 0.31612903
A17: County | B17: =COUNTIFS(Candidates!$E$2:$E$209,$A17,Candidates!$I$2:$I$209,">=0") -> 20 | C17: =COUNTIFS(Candidates!$E$2:$E$209,$A17,Candidates!$I$2:$I$209,">0.5") -> 14 | D17: =IFERROR(C17/B17,0) -> 0.7
A20: By party
B21: Statements | C21: Flagged | D21: Rate
A22: Democratic | B22: =COUNTIFS(Candidates!$B$2:$B$209,$A22,Candidates!$I$2:$I$209,">=0") -> 92 | C22: =COUNTIFS(Candidates!$B$2:$B$209,$A22,Candidates!$I$2:$I$209,">0.5") -> 36 | D22: =IFERROR(C22/B22,0) -> 0.39130435
A23: Republican | B23: =COUNTIFS(Candidates!$B$2:$B$209,$A23,Candidates!$I$2:$I$209,">=0") -> 91 | C23: =COUNTIFS(Candidates!$B$2:$B$209,$A23,Candidates!$I$2:$I$209,">0.5") -> 28 | D23: =IFERROR(C23/B23,0) -> 0.30769231
A24: Green | B24: =COUNTIFS(Candidates!$B$2:$B$209,$A24,Candidates!$I$2:$I$209,">=0") -> 6 | C24: =COUNTIFS(Candidates!$B$2:$B$209,$A24,Candidates!$I$2:$I$209,">0.5") -> 2 | D24: =IFERROR(C24/B24,0) -> 0.33333333
A25: Independent | B25: =COUNTIFS(Candidates!$B$2:$B$209,$A25,Candidates!$I$2:$I$209,">=0") -> 4 | C25: =COUNTIFS(Candidates!$B$2:$B$209,$A25,Candidates!$I$2:$I$209,">0.5") -> 1 | D25: =IFERROR(C25/B25,0) -> 0.25
A26: No Labels | B26: =COUNTIFS(Candidates!$B$2:$B$209,$A26,Candidates!$I$2:$I$209,">=0") -> 5 | C26: =COUNTIFS(Candidates!$B$2:$B$209,$A26,Candidates!$I$2:$I$209,">0.5") -> 3 | D26: =IFERROR(C26/B26,0) -> 0.6
A30: Distribution of AI scores
A31: Bin | B31: Statements
A32: 0%-5% | B32: =COUNTIFS(Candidates!$I$2:$I$209,">=0.0",Candidates!$I$2:$I$209,"<0.05") -> 121
A33: 5%-10% | B33: =COUNTIFS(Candidates!$I$2:$I$209,">=0.05",Candidates!$I$2:$I$209,"<0.1") -> 0
A34: 10%-15% | B34: =COUNTIFS(Candidates!$I$2:$I$209,">=0.1",Candidates!$I$2:$I$209,"<0.15000000000000002") -> 0
A35: 15%-20% | B35: =COUNTIFS(Candidates!$I$2:$I$209,">=0.15000000000000002",Candidates!$I$2:$I$209,"<0.2") -> 0
A36: 20%-25% | B36: =COUNTIFS(Candidates!$I$2:$I$209,">=0.2",Candidates!$I$2:$I$209,"<0.25") -> 1
A37: 25%-30% | B37: =COUNTIFS(Candidates!$I$2:$I$209,">=0.25",Candidates!$I$2:$I$209,"<0.30000000000000004") -> 1
A38: 30%-35% | B38: =COUNTIFS(Candidates!$I$2:$I$209,">=0.30000000000000004",Candidates!$I$2:$I$209,"<0.35000000000000003") -> 1
A39: 35%-40% | B39: =COUNTIFS(Candidates!$I$2:$I$209,">=0.35000000000000003",Candidates!$I$2:$I$209,"<0.4") -> 3
A40: 40%-45% | B40: =COUNTIFS(Candidates!$I$2:$I$209,">=0.4",Candidates!$I$2:$I$209,"<0.45") -> 0
A41: 45%-50% | B41: =COUNTIFS(Candidates!$I$2:$I$209,">=0.45",Candidates!$I$2:$I$209,"<0.5") -> 1
A42: 50%-55% | B42: =COUNTIFS(Candidates!$I$2:$I$209,">=0.5",Candidates!$I$2:$I$209,"<0.55") -> 1
A43: 55%-60% | B43: =COUNTIFS(Candidates!$I$2:$I$209,">=0.55",Candidates!$I$2:$I$209,"<0.6000000000000001") -> 2
A44: 60%-65% | B44: =COUNTIFS(Candidates!$I$2:$I$209,">=0.6000000000000001",Candidates!$I$2:$I$209,"<0.65") -> 0
A45: 65%-70% | B45: =COUNTIFS(Candidates!$I$2:$I$209,">=0.65",Candidates!$I$2:$I$209,"<0.7000000000000001") -> 3
A46: 70%-75% | B46: =COUNTIFS(Candidates!$I$2:$I$209,">=0.7000000000000001",Candidates!$I$2:$I$209,"<0.75") -> 0
A47: 75%-80% | B47: =COUNTIFS(Candidates!$I$2:$I$209,">=0.75",Candidates!$I$2:$I$209,"<0.8") -> 0
A48: 80%-85% | B48: =COUNTIFS(Candidates!$I$2:$I$209,">=0.8",Candidates!$I$2:$I$209,"<0.8500000000000001") -> 1
A49: 85%-90% | B49: =COUNTIFS(Candidates!$I$2:$I$209,">=0.8500000000000001",Candidates!$I$2:$I$209,"<0.9") -> 0
A50: 90%-95% | B50: =COUNTIFS(Candidates!$I$2:$I$209,">=0.9",Candidates!$I$2:$I$209,"<0.9500000000000001") -> 0
A51: 95%-100% | B51: =COUNTIFS(Candidates!$I$2:$I$209,">=0.9500000000000001",Candidates!$I$2:$I$209,"<=1.0") -> 63
